GIMMESolver.cp311-win_amd64.pyd
GIMMECore/Adaptation.py
GIMMECore/InteractionsProfile.py
GIMMECore/PlayerStructs.py
GIMMECore/__init__.py
GIMMECore/AlgDefStructs/ConfigsGenAlg.py
GIMMECore/AlgDefStructs/PlayerDataTrimAlg.py
GIMMECore/AlgDefStructs/PreferencesEstAlg.py
GIMMECore/AlgDefStructs/RegressionAlg.py
GIMMECore/AlgDefStructs/__init__.py
GIMMECore/ModelBridge/PlayerModelBridge.py
GIMMECore/ModelBridge/TaskModelBridge.py
GIMMECore/ModelBridge/__init__.py
GIMMECore-1.6.5.dist-info/LICENSE.md
GIMMECore-1.6.5.dist-info/METADATA
GIMMECore-1.6.5.dist-info/WHEEL
GIMMECore-1.6.5.dist-info/top_level.txt
GIMMECore-1.6.5.dist-info/RECORD
