Metadata-Version: 2.1
Name: GIMMECore
Version: 1.6.5
Summary: GIMME (Group Interactions Management for Multiplayer sErious games) is a research tool which focuses on the management of interactions in groups so that the collective ability improves.
Home-page: https://github.com/SamGomes/GIMME
Author: Samuel Gomes
Author-email: samuel.gomes@tecnico.ulisboa.pt
License: CC BY 4.0
Classifier: Development Status :: 4 - Beta
Classifier: Environment :: Console
Classifier: Intended Audience :: Science/Research
Classifier: Programming Language :: Python :: 3
Classifier: Topic :: Scientific/Engineering :: Artificial Intelligence
Requires-Python: >=3.7
License-File: LICENSE.md
Requires-Dist: python-decouple >=3.0
Requires-Dist: deap >=1.3.3
Requires-Dist: pandas >=1.3.5
Requires-Dist: scikit-learn >=1.0.2
Requires-Dist: matplotlib >=3.5.3
Requires-Dist: pymongo >=4.3.3
